ccd/__init__.py
ccd/app.py
ccd/change.py
ccd/math_utils.py
ccd/parameters.py
ccd/procedures.py
ccd/qa.py
ccd/version.py
ccd/models/__init__.py
ccd/models/lasso.py
ccd/models/robust_fit.py
ccd/models/tmask.py
lcmap_pyccd-2021.7.19.dist-info/LICENSE.md
lcmap_pyccd-2021.7.19.dist-info/METADATA
lcmap_pyccd-2021.7.19.dist-info/WHEEL
lcmap_pyccd-2021.7.19.dist-info/top_level.txt
lcmap_pyccd-2021.7.19.dist-info/RECORD
