Metadata-Version: 2.1
Name: lcmap-pyccd
Version: 2021.7.19
Summary: Python implementation of Continuous Change Detection
Home-page: https://code.usgs.gov/lcmap/pyccd
Maintainer: Kelcy Smith
Maintainer-email: klsmith@contractor.usgs.gov
License: Public Domain
Keywords: python change detection
Platform: UNKNOWN
Classifier: Development Status :: 5 - Production/Stable
Classifier: Intended Audience :: Developers
Classifier: License :: Public Domain
Classifier: Programming Language :: Python :: 3.4
Classifier: Programming Language :: Python :: 3.5
Classifier: Programming Language :: Python :: 3.6
License-File: LICENSE.md
Requires-Dist: numpy (>=1.10.0)
Requires-Dist: scipy (>=0.18.1)
Requires-Dist: scikit-learn (>=0.18)
Provides-Extra: deploy
Requires-Dist: twine ; extra == 'deploy'
Provides-Extra: dev
Requires-Dist: jupyter ; extra == 'dev'
Requires-Dist: line-profiler ; extra == 'dev'
Provides-Extra: docs
Requires-Dist: sphinx ; extra == 'docs'
Requires-Dist: sphinx-autobuild ; extra == 'docs'
Requires-Dist: sphinx-rtd-theme ; extra == 'docs'
Provides-Extra: test
Requires-Dist: aniso8601 (>=1.1.0) ; extra == 'test'
Requires-Dist: flake8 (>=3.0.4) ; extra == 'test'
Requires-Dist: coverage (>=4.2) ; extra == 'test'
Requires-Dist: pytest (>=3.0.2) ; extra == 'test'
Requires-Dist: pytest-profiling (>=1.1.1) ; extra == 'test'
Requires-Dist: gprof2dot (>=2015.12.1) ; extra == 'test'
Requires-Dist: pytest-watch (>=4.1.0) ; extra == 'test'
